yolo_world_onnx/__init__.py
yolo_world_onnx/model.py
yolo_world_onnx-0.1.1.dist-info/METADATA
yolo_world_onnx-0.1.1.dist-info/WHEEL
yolo_world_onnx-0.1.1.dist-info/top_level.txt
yolo_world_onnx-0.1.1.dist-info/RECORD
