Metadata-Version: 2.1
Name: yolo-world-onnx
Version: 0.1.1
Summary: ONNX-YOLO is a Python package for running inference on YOLO-WORLD open-vocabulary object detection models using ONNX runtime.
Home-page: https://github.com/Ziad-Algrafi/onnx-yolo
Author: Ziad-Algrafi
Author-email: ZiadAlgrafi@gmail.com
License: MIT
Classifier: Development Status :: 5 - Production/Stable
Classifier: Intended Audience :: Developers
Classifier: License :: OSI Approved :: MIT License
Classifier: Programming Language :: Python :: 3
Classifier: Programming Language :: Python :: 3.9
Classifier: Programming Language :: Python :: 3.10
Classifier: Programming Language :: Python :: 3.11
Classifier: Programming Language :: Python :: 3.12
Requires-Python: >=3.9
Requires-Dist: numpy
Requires-Dist: opencv-python
Requires-Dist: onnxruntime-gpu
Requires-Dist: torch >=1.7.0
Requires-Dist: torchvision >=0.8.0
Requires-Dist: clip-for-odlabel
